PyXGT/LS.py
PyXGT/__init__.py
PyXGT-1.1.dist-info/METADATA
PyXGT-1.1.dist-info/WHEEL
PyXGT-1.1.dist-info/top_level.txt
PyXGT-1.1.dist-info/RECORD
